simlr_py3/__init__.py
simlr_py3/core.py
simlr_py3/helper.py
simlr_py3-0.1.5.dist-info/LICENSE.txt
simlr_py3-0.1.5.dist-info/METADATA
simlr_py3-0.1.5.dist-info/WHEEL
simlr_py3-0.1.5.dist-info/top_level.txt
simlr_py3-0.1.5.dist-info/RECORD
