Metadata-Version: 2.1
Name: simlr-py3
Version: 0.1.5
Summary: Visualization and analysis of single-cell RNA-seq data by kernel-based similarity learning
Home-page: https://github.com/SIAT-BIT-CXH/SIMLR_PY
Author: Xuhang Chen
Author-email: cxhhg11@gmail.com
License: UNKNOWN
Platform: UNKNOWN
License-File: LICENSE.txt
Requires-Dist: fbpca (>=1.0)
Requires-Dist: numpy (>=1.8.0)
Requires-Dist: scipy (>=0.13.2)
Requires-Dist: annoy (>=1.8.0)
Requires-Dist: scikit-learn (>=0.17.1)
